[
{
		"name": "The Citadel",
		"isNationalWonder": true,
		"production": 15,
		"science": 15,
		"gold": 5000,
		"culture": 50,
	        "faith": 50,
		"cityStrength": 20,
		"cost": 1,
    "uniqueTo": "Citadellium"
		"uniques": ["Provides [20] [Digital Storage Space]",
			"Provides [10] [Digital Storage Space] <after discovering [Info Networks]>",
			"Provides [10] [Yairmite]",
			"Provides [10] [Gravitix]",
			"Provides [10] [Antimatter]",
			"Provides [10] [Ulframite]",
			"Provides [10] [Vitamass]",
			"Provides [10] [Promethine]",
			"Provides [10] [Titanium]",
			"Indicates the capital city"
		],
	},
{
  "name": "Citadellium Armaments",
  "replaces": "Frontier Armory",
  "uniqueTo": "Citadellium",
  "cost": 1,
  "uniques": ["Military", "New [Military] units start with [1500000000] Experience [in this city]"],
  "requiredTech": "Frontier Armaments",
},
]
